{
  "_id": "6d42d729-932d-490e-8206-37b20a00bec4",
  "name": "LHS Autogenerated 116",
  "run_start_time": "2020-04-26T09:19:42.052Z",
  "run_end_time": "2020-04-26T09:22:53.298Z",
  "status": "completed",
  "status_message": "completed normal",
  "create_bar_from_doe_building_type_ratios.building_rotation": 150.12507041227073,
  "create_bar_from_doe_building_type_ratios.ns_to_ew_ratio": 3.1888745006383394,
  "create_bar_from_doe_building_type_ratios.num_stories_above_grade": 2.0,
  "create_bar_from_doe_building_type_ratios.total_bldg_floor_area": 28851.45450598405,
  "create_bar_from_doe_building_type_ratios.wwr": 0.7186565262014046,
  "create_typical_doe_building_from_model.htg_src": "Electricity",
  "create_typical_doe_building_from_model.template": "90.1-2007",
  "create_typical_doe_building_from_model.wkdy_op_hrs_duration": 12.49901127697279,
  "create_typical_doe_building_from_model.wkdy_op_hrs_start_time": 6.515011250454312,
  "internal_loads_multiplier.lpd_multiplier": 5.837011918006852,
  "internal_loads_multiplier.people_per_floor_area_multiplier": 9.701939046912594,
  "dc_timeseries_reports.energyplus_runtime": 101.62,
  "openstudio_results.additional_fuel_ip": 0.0,
  "openstudio_results.annual_peak_electric_demand": 262.33603000000005,
  "openstudio_results.annual_utility_cost": 0.0,
  "openstudio_results.district_cooling_ip": 0.0,
  "openstudio_results.district_heating_ip": 0.0,
  "openstudio_results.electricity_ip": 849090.42867095,
  "openstudio_results.eui": 102.61886178322102,
  "openstudio_results.first_year_capital_cost": 0.0,
  "openstudio_results.natural_gas_ip": 63.49295142399188,
  "openstudio_results.net_site_energy": 2960705.8168939124,
  "openstudio_results.total_lifecycle_cost": 0.0,
  "openstudio_results.total_site_eui": 102.61886178322102,
  "openstudio_results.unmet_hours_during_occupied_cooling": 659.5,
  "openstudio_results.unmet_hours_during_occupied_heating": 210.67,
  "data_point_uuid": "/data_points/6d42d729-932d-490e-8206-37b20a00bec4"
}